climate_ref_pmp/__init__.py
climate_ref_pmp/pmp_driver.py
climate_ref_pmp/py.typed
climate_ref_pmp/dataset_registry/pmp_climatology.txt
climate_ref_pmp/diagnostics/__init__.py
climate_ref_pmp/diagnostics/annual_cycle.py
climate_ref_pmp/diagnostics/enso.py
climate_ref_pmp/diagnostics/variability_modes.py
climate_ref_pmp/drivers/enso_driver.py
climate_ref_pmp/params/pmp_param_MoV-psl.py
climate_ref_pmp/params/pmp_param_MoV-ts.py
climate_ref_pmp/params/pmp_param_annualcycle_1-clims.py
climate_ref_pmp/params/pmp_param_annualcycle_2-metrics.py
climate_ref_pmp/requirements/conda-lock.yml
climate_ref_pmp/requirements/environment.yml
climate_ref_pmp-0.8.1.dist-info/METADATA
climate_ref_pmp-0.8.1.dist-info/WHEEL
climate_ref_pmp-0.8.1.dist-info/entry_points.txt
climate_ref_pmp-0.8.1.dist-info/licenses/LICENCE
climate_ref_pmp-0.8.1.dist-info/licenses/NOTICE
climate_ref_pmp-0.8.1.dist-info/RECORD
